scc_whisper_api_client/__init__.py
scc_whisper_api_client/client.py
scc_whisper_api_client/config.py
scc_whisper_api_client/models.py
scc_whisper_api_client/synchronous_client.py
scc_whisper_api_client-0.2.8.dist-info/METADATA
scc_whisper_api_client-0.2.8.dist-info/WHEEL
scc_whisper_api_client-0.2.8.dist-info/RECORD
